flask_cbv/__init__.py
flask_classical-0.1.0.dist-info/LICENSE
flask_classical-0.1.0.dist-info/METADATA
flask_classical-0.1.0.dist-info/WHEEL
flask_classical-0.1.0.dist-info/RECORD
