Metadata-Version: 2.1
Name: Flask-Classical
Version: 0.1.0
Summary: Flask extension for providing class-based views
Author: Rafal Padkowski
Author-email: rafaelp@poczta.onet.pl
Requires-Python: >=3.10
Classifier: Programming Language :: Python :: 3
Classifier: Programming Language :: Python :: 3.10
Classifier: Programming Language :: Python :: 3.11
Classifier: Programming Language :: Python :: 3.12
Requires-Dist: flask (>=3.0.0)
Requires-Dist: flask-auxs (>=0.1.0)
